odoo/addons/mgmtsystem_hazard_maintenance_equipment/README.rst
odoo/addons/mgmtsystem_hazard_maintenance_equipment/__init__.py
odoo/addons/mgmtsystem_hazard_maintenance_equipment/__manifest__.py
odoo/addons/mgmtsystem_hazard_maintenance_equipment/i18n/it.po
odoo/addons/mgmtsystem_hazard_maintenance_equipment/i18n/mgmtsystem_hazard_maintenance_equipment.pot
odoo/addons/mgmtsystem_hazard_maintenance_equipment/models/__init__.py
odoo/addons/mgmtsystem_hazard_maintenance_equipment/models/mgmtsystem_hazard.py
odoo/addons/mgmtsystem_hazard_maintenance_equipment/readme/CONTRIBUTORS.rst
odoo/addons/mgmtsystem_hazard_maintenance_equipment/readme/DESCRIPTION.rst
odoo/addons/mgmtsystem_hazard_maintenance_equipment/readme/USAGE.rst
odoo/addons/mgmtsystem_hazard_maintenance_equipment/static/description/icon.png
odoo/addons/mgmtsystem_hazard_maintenance_equipment/static/description/index.html
odoo/addons/mgmtsystem_hazard_maintenance_equipment/views/mgmtsystem_hazard.xml
odoo_addon_mgmtsystem_hazard_maintenance_equipment-16.0.1.0.0.4.dist-info/METADATA
odoo_addon_mgmtsystem_hazard_maintenance_equipment-16.0.1.0.0.4.dist-info/WHEEL
odoo_addon_mgmtsystem_hazard_maintenance_equipment-16.0.1.0.0.4.dist-info/top_level.txt
odoo_addon_mgmtsystem_hazard_maintenance_equipment-16.0.1.0.0.4.dist-info/RECORD
